{
  "Microsoft": 0,
  "S&P Global": 0,
  "FIS Global": 0,
  "Invesco": 0,
  "Autodesk": 2,
  "Micron": 0,
  "Fiserv": 0,
  "Sabre": 0,
  "Broadridge": 0,
  "Ameriprise": 0,
  "Lowe's": 0,
  "Citi": 0,
  "General Motors": 2,
  "Adobe": 0,
  "Fidelity": 0,
  "Northern Trust": 0,
  "Target": 2,
  "Marsh McLennan": 0,
  "Kyndryl": 0,
  "eBay": 0,
  "State Street": 0,
  "Synchrony": 0,
  "Wells Fargo": 0,
  "Barclays": 0,
  "PayPal": 2,
  "First American": 3,
  "DXC Technology": 0,
  "Mastercard": 2,
  "Maersk": 0,
  "LSEG": 0
}